{
  "post_id": "3903851672438823998",
  "organizer_id": "la-little-lion-social-club",
  "platform": "instagram",
  "posted_at": "2026-05-24T04:07:24.000Z",
  "text": "Wow, what an amazing turnout today for our Shih Tzu meet up in LA! Big shout out to @pawradise.park for hosting us and @littlemisseunie for organizing! It’s evident how much love we all have for our Shih Tzu’s 🥰 appreciate everyone for making the effort today, and if you weren’t able to join us today, the next meet up was just announced 👀",
  "image_urls": [
    "https://scontent-mia3-3.cdninstagram.com/v/t51.82787-15/707617777_17990999591985584_1938768991610495338_n.jpg?stp=dst-jpg_e15_tt6&_nc_ht=scontent-mia3-3.cdninstagram.com&_nc_cat=108&_nc_oc=Q6cZ2gHbTwlUBypRKJZ4LVs79vSmSlHnwWKUsS0bwYu06I5W0zBlc55Nz0eCpUgEhdBCa5s&_nc_ohc=uqWQcdE6ig0Q7kNvwGAfjbS&_nc_gid=c7sYcZVC8wuT5znakOi94Q&edm=APs17CUBAAAA&ccb=7-5&oh=00_Af_YIOLtq8EnKvvqDM5A8bHY3MoQ1Nitc_bqYB4WNHluAw&oe=6A3C75D1&_nc_sid=10d13b"
  ],
  "permalink": "https://www.instagram.com/p/DYtRGmfh9w-/"
}
